anywidget_cad_viewer/__init__.py
anywidget_cad_viewer/geometry.py
anywidget_cad_viewer/py.typed
anywidget_cad_viewer/viewer.py
anywidget_cad_viewer/static/README.md
anywidget_cad_viewer/static/index.css
anywidget_cad_viewer/static/index.js
anywidget_cad_viewer-0.1.0.dist-info/licenses/LICENSE
anywidget_cad_viewer-0.1.0.dist-info/METADATA
anywidget_cad_viewer-0.1.0.dist-info/WHEEL
anywidget_cad_viewer-0.1.0.dist-info/top_level.txt
anywidget_cad_viewer-0.1.0.dist-info/RECORD
