Metadata-Version: 2.4
Name: anywidget-cad-viewer
Version: 0.1.0
Summary: An anywidget-based CAD viewer for visualizing build123d objects in marimo and Jupyter notebooks
Author: anywidget-cad-viewer contributors
Project-URL: Homepage, https://github.com/casey-SK/anywidget-cad-viewer
Project-URL: Repository, https://github.com/casey-SK/anywidget-cad-viewer
Project-URL: Issues, https://github.com/casey-SK/anywidget-cad-viewer/issues
Keywords: anywidget,cad,build123d,marimo,jupyter,3d-visualization
Classifier: Development Status :: 3 - Alpha
Classifier: Intended Audience :: Developers
Classifier: Topic :: Scientific/Engineering :: Visualization
Classifier: License :: OSI Approved :: MIT License
Classifier: Programming Language :: Python :: 3
Classifier: Programming Language :: Python :: 3.13
Requires-Python: >=3.13
License-File: LICENSE
Requires-Dist: anywidget>=0.9.21
Requires-Dist: build123d>=0.10.0
Dynamic: license-file
